[{"item_id":1,"name":"pistachio","category":"Fashion","Warehouse":"WH3","stock_level":496,"last_update":"2025-06-09T02:26:22Z"},
{"item_id":2,"name":"sweets","category":"Vegetables","Warehouse":"WH4","stock_level":326,"last_update":"2025-06-13T00:49:56Z"},
{"item_id":3,"name":"mangosteen","category":"Sweets","Warehouse":"WH5","stock_level":230,"last_update":"2025-06-29T17:57:53Z"},
{"item_id":4,"name":"kidney bean","category":"Ice creams","Warehouse":"WH4","stock_level":484,"last_update":"2025-06-24T19:03:27Z"},
{"item_id":5,"name":"millet","category":"Dry fruits","Warehouse":"WH2","stock_level":447,"last_update":"2025-06-09T15:24:10Z"},
{"item_id":6,"name":"rye","category":"Ice creams","Warehouse":"WH5","stock_level":270,"last_update":"2025-06-17T15:27:50Z"},
{"item_id":7,"name":"toys","category":"Fruits","Warehouse":"WH5","stock_level":164,"last_update":"2025-06-06T12:23:52Z"},
{"item_id":8,"name":"lentil","category":"Electronic Items","Warehouse":"WH3","stock_level":375,"last_update":"2025-06-26T07:28:13Z"},
{"item_id":9,"name":"electronic items","category":"Toys","Warehouse":"WH5","stock_level":167,"last_update":"2025-06-06T15:15:39Z"},
{"item_id":10,"name":"cabbage","category":"Dry fruits","Warehouse":"WH1","stock_level":382,"last_update":"2025-06-20T22:38:26Z"},
{"item_id":11,"name":"turmeric","category":"Groceries","Warehouse":"WH2","stock_level":182,"last_update":"2025-06-24T23:39:31Z"},
{"item_id":12,"name":"rice","category":"Fashion","Warehouse":"WH3","stock_level":233,"last_update":"2025-06-04T04:33:11Z"},
{"item_id":13,"name":"plum","category":"Toys","Warehouse":"WH2","stock_level":83,"last_update":"2025-06-13T03:38:34Z"},
{"item_id":14,"name":"jalapeno","category":"Ice creams","Warehouse":"WH5","stock_level":80,"last_update":"2025-06-03T03:53:12Z"},
{"item_id":15,"name":"corn","category":"Electronic Items","Warehouse":"WH4","stock_level":33,"last_update":"2025-06-04T09:20:18Z"},
{"item_id":16,"name":"fava bean","category":"Packaged food","Warehouse":"WH4","stock_level":383,"last_update":"2025-06-13T23:32:53Z"},
{"item_id":17,"name":"carrot","category":"Groceries","Warehouse":"WH4","stock_level":51,"last_update":"2025-06-27T07:01:55Z"},
{"item_id":18,"name":"blackberry","category":"Fruits","Warehouse":"WH4","stock_level":294,"last_update":"2025-06-17T22:32:01Z"},
{"item_id":19,"name":"macadamia","category":"Packaged food","Warehouse":"WH5","stock_level":415,"last_update":"2025-06-03T16:16:23Z"},
{"item_id":20,"name":"spinach","category":"Toys","Warehouse":"WH5","stock_level":28,"last_update":"2025-06-02T21:17:14Z"},
{"item_id":21,"name":"lemon","category":"Ice creams","Warehouse":"WH3","stock_level":171,"last_update":"2025-06-11T18:02:43Z"},
{"item_id":22,"name":"lentil","category":"Sweets","Warehouse":"WH4","stock_level":462,"last_update":"2025-06-11T07:00:19Z"},
{"item_id":23,"name":"kale","category":"Ice creams","Warehouse":"WH1","stock_level":479,"last_update":"2025-06-19T07:41:23Z"},
{"item_id":24,"name":"watermelon","category":"Fashion","Warehouse":"WH2","stock_level":216,"last_update":"2025-06-03T19:51:30Z"},
{"item_id":25,"name":"eggplant","category":"Vegetables","Warehouse":"WH1","stock_level":6,"last_update":"2025-06-22T09:17:56Z"},
{"item_id":26,"name":"pecan","category":"Toys","Warehouse":"WH3","stock_level":416,"last_update":"2025-06-17T19:10:46Z"},
{"item_id":27,"name":"starfruit","category":"Dry fruits","Warehouse":"WH5","stock_level":393,"last_update":"2025-06-23T21:35:42Z"},
{"item_id":28,"name":"packaged food","category":"Toys","Warehouse":"WH5","stock_level":221,"last_update":"2025-06-02T11:11:05Z"},
{"item_id":29,"name":"navy bean","category":"Fruits","Warehouse":"WH1","stock_level":429,"last_update":"2025-06-03T00:24:13Z"},
{"item_id":30,"name":"split pea","category":"Vegetables","Warehouse":"WH1","stock_level":436,"last_update":"2025-06-04T21:03:06Z"},
{"item_id":31,"name":"turmeric","category":"Sweets","Warehouse":"WH4","stock_level":4,"last_update":"2025-06-09T10:51:48Z"},
{"item_id":32,"name":"eggplant","category":"Dry fruits","Warehouse":"WH3","stock_level":181,"last_update":"2025-06-24T11:20:12Z"},
{"item_id":33,"name":"macadamia","category":"Dry fruits","Warehouse":"WH2","stock_level":119,"last_update":"2025-06-23T05:09:47Z"},
{"item_id":34,"name":"lime","category":"Sweets","Warehouse":"WH5","stock_level":36,"last_update":"2025-06-22T19:23:03Z"},
{"item_id":35,"name":"kidney bean","category":"Vegetables","Warehouse":"WH5","stock_level":307,"last_update":"2025-06-01T13:37:33Z"},
{"item_id":36,"name":"apple","category":"Electronic Items","Warehouse":"WH3","stock_level":247,"last_update":"2025-06-26T03:58:12Z"},
{"item_id":37,"name":"eggplant","category":"Electronic Items","Warehouse":"WH4","stock_level":290,"last_update":"2025-06-28T21:46:42Z"},
{"item_id":38,"name":"spinach","category":"Sweets","Warehouse":"WH2","stock_level":491,"last_update":"2025-06-16T14:43:21Z"},
{"item_id":39,"name":"avocado","category":"Electronic Items","Warehouse":"WH2","stock_level":13,"last_update":"2025-06-07T08:17:42Z"},
{"item_id":40,"name":"lentil","category":"Packaged food","Warehouse":"WH4","stock_level":444,"last_update":"2025-06-05T08:40:25Z"},
{"item_id":41,"name":"coriander","category":"Electronic Items","Warehouse":"WH2","stock_level":85,"last_update":"2025-06-11T19:22:28Z"},
{"item_id":42,"name":"amaranth","category":"Groceries","Warehouse":"WH2","stock_level":317,"last_update":"2025-06-01T10:07:07Z"},
{"item_id":43,"name":"broccoli","category":"Ice creams","Warehouse":"WH5","stock_level":367,"last_update":"2025-06-22T05:01:47Z"},
{"item_id":44,"name":"apple","category":"Sweets","Warehouse":"WH1","stock_level":2,"last_update":"2025-06-29T17:15:06Z"},
{"item_id":45,"name":"sesame seed","category":"Fashion","Warehouse":"WH2","stock_level":162,"last_update":"2025-06-07T08:45:50Z"},
{"item_id":46,"name":"honeydew","category":"Groceries","Warehouse":"WH5","stock_level":362,"last_update":"2025-06-01T00:47:02Z"},
{"item_id":47,"name":"passionfruit","category":"Fruits","Warehouse":"WH5","stock_level":388,"last_update":"2025-06-11T19:47:25Z"},
{"item_id":48,"name":"passionfruit","category":"Fashion","Warehouse":"WH4","stock_level":4,"last_update":"2025-06-02T20:26:03Z"},
{"item_id":49,"name":"quinoa","category":"Ice creams","Warehouse":"WH5","stock_level":21,"last_update":"2025-06-13T07:42:06Z"},
{"item_id":50,"name":"pineapple","category":"Vegetables","Warehouse":"WH1","stock_level":214,"last_update":"2025-06-04T20:47:54Z"},
{"item_id":51,"name":"dry fruits","category":"Toys","Warehouse":"WH5","stock_level":282,"last_update":"2025-06-05T15:16:21Z"},
{"item_id":52,"name":"kale","category":"Packaged food","Warehouse":"WH2","stock_level":216,"last_update":"2025-06-23T05:29:50Z"},
{"item_id":53,"name":"cucumber","category":"Groceries","Warehouse":"WH2","stock_level":332,"last_update":"2025-06-21T23:21:17Z"},
{"item_id":54,"name":"ice creams","category":"Fashion","Warehouse":"WH5","stock_level":467,"last_update":"2025-06-07T21:47:37Z"},
{"item_id":55,"name":"honeydew","category":"Fashion","Warehouse":"WH1","stock_level":239,"last_update":"2025-06-13T13:30:47Z"},
{"item_id":56,"name":"starfruit","category":"Sweets","Warehouse":"WH2","stock_level":133,"last_update":"2025-06-28T02:27:03Z"},
{"item_id":57,"name":"dry fruits","category":"Electronic Items","Warehouse":"WH5","stock_level":33,"last_update":"2025-06-16T19:33:40Z"},
{"item_id":58,"name":"ginger","category":"Vegetables","Warehouse":"WH2","stock_level":388,"last_update":"2025-06-05T02:57:22Z"},
{"item_id":59,"name":"durian","category":"Toys","Warehouse":"WH5","stock_level":464,"last_update":"2025-06-11T13:08:22Z"},
{"item_id":60,"name":"starfruit","category":"Groceries","Warehouse":"WH3","stock_level":0,"last_update":"2025-06-20T16:13:39Z"},
{"item_id":61,"name":"cashew","category":"Groceries","Warehouse":"WH5","stock_level":254,"last_update":"2025-06-28T13:03:06Z"},
{"item_id":62,"name":"spinach","category":"Vegetables","Warehouse":"WH5","stock_level":351,"last_update":"2025-06-19T19:32:42Z"},
{"item_id":63,"name":"spelt","category":"Vegetables","Warehouse":"WH5","stock_level":447,"last_update":"2025-06-24T21:07:03Z"},
{"item_id":64,"name":"lemon","category":"Fashion","Warehouse":"WH4","stock_level":194,"last_update":"2025-06-04T02:30:08Z"},
{"item_id":65,"name":"almond","category":"Toys","Warehouse":"WH3","stock_level":443,"last_update":"2025-06-02T02:36:21Z"},
{"item_id":66,"name":"coriander","category":"Dry fruits","Warehouse":"WH1","stock_level":417,"last_update":"2025-06-20T19:07:00Z"},
{"item_id":67,"name":"dragonfruit","category":"Sweets","Warehouse":"WH2","stock_level":167,"last_update":"2025-06-21T00:52:00Z"},
{"item_id":68,"name":"turmeric","category":"Groceries","Warehouse":"WH2","stock_level":457,"last_update":"2025-06-21T00:34:42Z"},
{"item_id":69,"name":"nutmeg","category":"Fruits","Warehouse":"WH1","stock_level":15,"last_update":"2025-06-09T08:40:16Z"},
{"item_id":70,"name":"passionfruit","category":"Dry fruits","Warehouse":"WH4","stock_level":123,"last_update":"2025-06-19T17:09:45Z"},
{"item_id":71,"name":"electronic items","category":"Fruits","Warehouse":"WH4","stock_level":342,"last_update":"2025-06-22T03:02:59Z"},
{"item_id":72,"name":"watermelon","category":"Toys","Warehouse":"WH3","stock_level":170,"last_update":"2025-06-11T13:08:46Z"},
{"item_id":73,"name":"rosemary","category":"Electronic Items","Warehouse":"WH4","stock_level":424,"last_update":"2025-06-13T04:43:11Z"},
{"item_id":74,"name":"toys","category":"Fruits","Warehouse":"WH2","stock_level":23,"last_update":"2025-06-04T20:25:58Z"},
{"item_id":75,"name":"fig","category":"Vegetables","Warehouse":"WH3","stock_level":54,"last_update":"2025-06-07T09:24:05Z"},
{"item_id":76,"name":"black bean","category":"Toys","Warehouse":"WH1","stock_level":23,"last_update":"2025-06-24T05:30:08Z"},
{"item_id":77,"name":"parsley","category":"Electronic Items","Warehouse":"WH5","stock_level":433,"last_update":"2025-06-03T07:05:30Z"},
{"item_id":78,"name":"peach","category":"Fruits","Warehouse":"WH2","stock_level":18,"last_update":"2025-06-25T13:45:36Z"},
{"item_id":79,"name":"kidney bean","category":"Vegetables","Warehouse":"WH2","stock_level":89,"last_update":"2025-06-25T06:08:08Z"},
{"item_id":80,"name":"eggplant","category":"Groceries","Warehouse":"WH1","stock_level":150,"last_update":"2025-06-09T16:24:10Z"},
{"item_id":81,"name":"cauliflower","category":"Dry fruits","Warehouse":"WH2","stock_level":35,"last_update":"2025-06-24T21:12:40Z"},
{"item_id":82,"name":"cayenne","category":"Vegetables","Warehouse":"WH2","stock_level":202,"last_update":"2025-06-08T17:48:40Z"},
{"item_id":83,"name":"potato","category":"Dry fruits","Warehouse":"WH2","stock_level":240,"last_update":"2025-06-18T05:37:36Z"},
{"item_id":84,"name":"sesame seed","category":"Vegetables","Warehouse":"WH2","stock_level":160,"last_update":"2025-06-10T04:27:49Z"},
{"item_id":85,"name":"blackberry","category":"Groceries","Warehouse":"WH3","stock_level":451,"last_update":"2025-06-13T04:02:38Z"},
{"item_id":86,"name":"chia seed","category":"Packaged food","Warehouse":"WH3","stock_level":231,"last_update":"2025-06-01T02:23:59Z"},
{"item_id":87,"name":"walnut","category":"Ice creams","Warehouse":"WH5","stock_level":392,"last_update":"2025-06-16T16:41:03Z"},
{"item_id":88,"name":"bay leaf","category":"Sweets","Warehouse":"WH5","stock_level":399,"last_update":"2025-06-05T12:55:44Z"},
{"item_id":89,"name":"pomegranate","category":"Toys","Warehouse":"WH5","stock_level":122,"last_update":"2025-06-21T01:40:59Z"},
{"item_id":90,"name":"split pea","category":"Dry fruits","Warehouse":"WH3","stock_level":55,"last_update":"2025-06-01T19:23:16Z"},
{"item_id":91,"name":"chickpea","category":"Groceries","Warehouse":"WH2","stock_level":185,"last_update":"2025-06-22T18:02:07Z"},
{"item_id":92,"name":"split pea","category":"Electronic Items","Warehouse":"WH4","stock_level":307,"last_update":"2025-06-16T15:59:29Z"},
{"item_id":93,"name":"vanilla","category":"Sweets","Warehouse":"WH4","stock_level":370,"last_update":"2025-06-29T12:07:25Z"},
{"item_id":94,"name":"bay leaf","category":"Sweets","Warehouse":"WH5","stock_level":404,"last_update":"2025-06-04T05:26:26Z"},
{"item_id":95,"name":"dry fruits","category":"Dry fruits","Warehouse":"WH4","stock_level":162,"last_update":"2025-06-22T17:23:36Z"},
{"item_id":96,"name":"sesame seed","category":"Electronic Items","Warehouse":"WH1","stock_level":156,"last_update":"2025-06-17T21:50:35Z"},
{"item_id":97,"name":"tomato","category":"Fruits","Warehouse":"WH4","stock_level":110,"last_update":"2025-06-22T16:50:58Z"},
{"item_id":98,"name":"buckwheat","category":"Sweets","Warehouse":"WH3","stock_level":391,"last_update":"2025-06-11T20:10:00Z"},
{"item_id":99,"name":"parsley","category":"Electronic Items","Warehouse":"WH1","stock_level":124,"last_update":"2025-06-15T14:56:18Z"},
{"item_id":100,"name":"potato","category":"Fruits","Warehouse":"WH3","stock_level":77,"last_update":"2025-06-28T22:59:44Z"},
{"item_id":101,"name":"black-eyed pea","category":"Groceries","Warehouse":"WH1","stock_level":465,"last_update":"2025-06-12T22:17:52Z"},
{"item_id":102,"name":"buckwheat","category":"Fashion","Warehouse":"WH3","stock_level":342,"last_update":"2025-06-25T11:21:20Z"},
{"item_id":103,"name":"cucumber","category":"Packaged food","Warehouse":"WH3","stock_level":162,"last_update":"2025-06-15T06:25:57Z"},
{"item_id":104,"name":"jalapeno","category":"Toys","Warehouse":"WH4","stock_level":144,"last_update":"2025-06-12T08:34:11Z"},
{"item_id":105,"name":"carrot","category":"Fashion","Warehouse":"WH1","stock_level":315,"last_update":"2025-06-15T04:15:33Z"},
{"item_id":106,"name":"peach","category":"Fruits","Warehouse":"WH1","stock_level":92,"last_update":"2025-06-04T16:06:09Z"},
{"item_id":107,"name":"lime","category":"Vegetables","Warehouse":"WH2","stock_level":88,"last_update":"2025-06-06T05:59:10Z"},
{"item_id":108,"name":"packaged food","category":"Fashion","Warehouse":"WH3","stock_level":62,"last_update":"2025-06-26T14:38:43Z"},
{"item_id":109,"name":"mango","category":"Dry fruits","Warehouse":"WH4","stock_level":417,"last_update":"2025-06-15T17:17:17Z"},
{"item_id":110,"name":"sunflower seed","category":"Packaged food","Warehouse":"WH1","stock_level":279,"last_update":"2025-06-15T03:45:38Z"},
{"item_id":111,"name":"grape","category":"Toys","Warehouse":"WH4","stock_level":449,"last_update":"2025-06-02T16:58:28Z"},
{"item_id":112,"name":"lima bean","category":"Ice creams","Warehouse":"WH4","stock_level":18,"last_update":"2025-06-19T22:21:46Z"},
{"item_id":113,"name":"kidney bean","category":"Electronic Items","Warehouse":"WH2","stock_level":414,"last_update":"2025-06-01T10:04:18Z"},
{"item_id":114,"name":"cashew","category":"Fruits","Warehouse":"WH1","stock_level":399,"last_update":"2025-06-16T10:38:55Z"},
{"item_id":115,"name":"mustard","category":"Dry fruits","Warehouse":"WH4","stock_level":222,"last_update":"2025-06-25T19:47:46Z"},
{"item_id":116,"name":"lima bean","category":"Sweets","Warehouse":"WH2","stock_level":246,"last_update":"2025-06-20T12:19:42Z"},
{"item_id":117,"name":"cherry","category":"Sweets","Warehouse":"WH5","stock_level":22,"last_update":"2025-06-17T05:42:28Z"},
{"item_id":118,"name":"adzuki bean","category":"Vegetables","Warehouse":"WH4","stock_level":231,"last_update":"2025-06-19T13:02:26Z"},
{"item_id":119,"name":"avocado","category":"Electronic Items","Warehouse":"WH4","stock_level":233,"last_update":"2025-06-25T10:44:03Z"},
{"item_id":120,"name":"split pea","category":"Vegetables","Warehouse":"WH5","stock_level":68,"last_update":"2025-06-22T10:53:17Z"},
{"item_id":121,"name":"pinto bean","category":"Groceries","Warehouse":"WH2","stock_level":133,"last_update":"2025-06-23T20:25:13Z"},
{"item_id":122,"name":"jalapeno","category":"Electronic Items","Warehouse":"WH2","stock_level":63,"last_update":"2025-06-03T17:04:47Z"},
{"item_id":123,"name":"guava","category":"Vegetables","Warehouse":"WH3","stock_level":440,"last_update":"2025-06-11T05:42:17Z"},
{"item_id":124,"name":"honeydew","category":"Vegetables","Warehouse":"WH3","stock_level":8,"last_update":"2025-06-08T19:55:51Z"},
{"item_id":125,"name":"peanut","category":"Dry fruits","Warehouse":"WH5","stock_level":385,"last_update":"2025-06-19T00:45:35Z"},
{"item_id":126,"name":"breadfruit","category":"Dry fruits","Warehouse":"WH3","stock_level":110,"last_update":"2025-06-02T04:19:06Z"},
{"item_id":127,"name":"jalapeno","category":"Dry fruits","Warehouse":"WH4","stock_level":361,"last_update":"2025-06-03T11:28:59Z"},
{"item_id":128,"name":"basil","category":"Groceries","Warehouse":"WH4","stock_level":432,"last_update":"2025-06-26T19:27:07Z"},
{"item_id":129,"name":"bay leaf","category":"Fruits","Warehouse":"WH2","stock_level":474,"last_update":"2025-06-16T04:25:20Z"},
{"item_id":130,"name":"coriander","category":"Sweets","Warehouse":"WH2","stock_level":297,"last_update":"2025-06-14T17:39:57Z"},
{"item_id":131,"name":"hazelnut","category":"Ice creams","Warehouse":"WH2","stock_level":40,"last_update":"2025-06-17T22:56:53Z"},
{"item_id":132,"name":"lemon","category":"Electronic Items","Warehouse":"WH4","stock_level":394,"last_update":"2025-06-20T01:32:02Z"},
{"item_id":133,"name":"lychee","category":"Vegetables","Warehouse":"WH1","stock_level":65,"last_update":"2025-06-03T00:40:57Z"},
{"item_id":134,"name":"mangosteen","category":"Vegetables","Warehouse":"WH4","stock_level":475,"last_update":"2025-06-24T17:20:35Z"},
{"item_id":135,"name":"peach","category":"Groceries","Warehouse":"WH1","stock_level":83,"last_update":"2025-06-28T14:35:18Z"},
{"item_id":136,"name":"vanilla","category":"Dry fruits","Warehouse":"WH2","stock_level":15,"last_update":"2025-06-23T00:27:42Z"},
{"item_id":137,"name":"blueberry","category":"Electronic Items","Warehouse":"WH4","stock_level":39,"last_update":"2025-06-24T20:37:40Z"},
{"item_id":138,"name":"mustard","category":"Electronic Items","Warehouse":"WH1","stock_level":123,"last_update":"2025-06-11T08:41:49Z"},
{"item_id":139,"name":"chickpea","category":"Packaged food","Warehouse":"WH2","stock_level":69,"last_update":"2025-06-02T14:14:29Z"},
{"item_id":140,"name":"adzuki bean","category":"Sweets","Warehouse":"WH2","stock_level":197,"last_update":"2025-06-09T09:58:53Z"},
{"item_id":141,"name":"guava","category":"Groceries","Warehouse":"WH3","stock_level":23,"last_update":"2025-06-12T03:08:38Z"},
{"item_id":142,"name":"sweets","category":"Toys","Warehouse":"WH2","stock_level":292,"last_update":"2025-06-29T01:51:39Z"},
{"item_id":143,"name":"macadamia","category":"Ice creams","Warehouse":"WH2","stock_level":47,"last_update":"2025-06-15T05:00:20Z"},
{"item_id":144,"name":"electronic items","category":"Groceries","Warehouse":"WH3","stock_level":406,"last_update":"2025-06-19T09:14:35Z"},
{"item_id":145,"name":"thyme","category":"Toys","Warehouse":"WH4","stock_level":428,"last_update":"2025-06-07T01:37:35Z"},
{"item_id":146,"name":"mustard","category":"Toys","Warehouse":"WH3","stock_level":224,"last_update":"2025-06-06T05:59:53Z"},
{"item_id":147,"name":"hazelnut","category":"Toys","Warehouse":"WH5","stock_level":476,"last_update":"2025-06-12T07:33:46Z"},
{"item_id":148,"name":"bay leaf","category":"Packaged food","Warehouse":"WH1","stock_level":18,"last_update":"2025-06-17T04:15:10Z"},
{"item_id":149,"name":"amaranth","category":"Packaged food","Warehouse":"WH2","stock_level":411,"last_update":"2025-06-02T17:01:13Z"},
{"item_id":150,"name":"bulgur","category":"Vegetables","Warehouse":"WH3","stock_level":30,"last_update":"2025-06-12T16:22:45Z"},
{"item_id":151,"name":"lentil","category":"Vegetables","Warehouse":"WH4","stock_level":487,"last_update":"2025-06-11T17:34:44Z"},
{"item_id":152,"name":"blackberry","category":"Vegetables","Warehouse":"WH5","stock_level":184,"last_update":"2025-06-16T04:35:32Z"},
{"item_id":153,"name":"split pea","category":"Sweets","Warehouse":"WH2","stock_level":461,"last_update":"2025-06-14T03:05:41Z"},
{"item_id":154,"name":"avocado","category":"Ice creams","Warehouse":"WH1","stock_level":355,"last_update":"2025-06-27T05:48:03Z"},
{"item_id":155,"name":"almond","category":"Vegetables","Warehouse":"WH4","stock_level":294,"last_update":"2025-06-19T16:10:41Z"},
{"item_id":156,"name":"orange","category":"Packaged food","Warehouse":"WH2","stock_level":174,"last_update":"2025-06-25T06:33:46Z"},
{"item_id":157,"name":"apricot","category":"Toys","Warehouse":"WH5","stock_level":451,"last_update":"2025-06-03T02:57:43Z"},
{"item_id":158,"name":"cinnamon","category":"Fruits","Warehouse":"WH5","stock_level":218,"last_update":"2025-06-02T21:54:05Z"},
{"item_id":159,"name":"spinach","category":"Fashion","Warehouse":"WH1","stock_level":249,"last_update":"2025-06-23T07:49:29Z"},
{"item_id":160,"name":"farro","category":"Electronic Items","Warehouse":"WH2","stock_level":449,"last_update":"2025-06-09T23:57:16Z"},
{"item_id":161,"name":"cinnamon","category":"Toys","Warehouse":"WH1","stock_level":287,"last_update":"2025-06-21T06:39:50Z"},
{"item_id":162,"name":"couscous","category":"Ice creams","Warehouse":"WH2","stock_level":289,"last_update":"2025-06-24T18:50:48Z"},
{"item_id":163,"name":"chia seed","category":"Packaged food","Warehouse":"WH3","stock_level":470,"last_update":"2025-06-07T21:45:36Z"},
{"item_id":164,"name":"rosemary","category":"Ice creams","Warehouse":"WH2","stock_level":393,"last_update":"2025-06-28T09:18:38Z"},
{"item_id":165,"name":"split pea","category":"Packaged food","Warehouse":"WH5","stock_level":388,"last_update":"2025-06-20T12:04:40Z"},
{"item_id":166,"name":"pear","category":"Fashion","Warehouse":"WH3","stock_level":377,"last_update":"2025-06-22T06:28:55Z"},
{"item_id":167,"name":"mustard","category":"Fruits","Warehouse":"WH4","stock_level":222,"last_update":"2025-06-03T10:39:32Z"},
{"item_id":168,"name":"farro","category":"Toys","Warehouse":"WH3","stock_level":143,"last_update":"2025-06-09T06:05:23Z"},
{"item_id":169,"name":"bulgur","category":"Sweets","Warehouse":"WH5","stock_level":55,"last_update":"2025-06-29T14:58:34Z"},
{"item_id":170,"name":"kiwi","category":"Vegetables","Warehouse":"WH4","stock_level":133,"last_update":"2025-06-05T04:39:50Z"},
{"item_id":171,"name":"toys","category":"Toys","Warehouse":"WH1","stock_level":184,"last_update":"2025-06-19T06:36:07Z"},
{"item_id":172,"name":"papaya","category":"Ice creams","Warehouse":"WH2","stock_level":211,"last_update":"2025-06-13T13:40:58Z"},
{"item_id":173,"name":"fava bean","category":"Fruits","Warehouse":"WH4","stock_level":323,"last_update":"2025-06-10T17:02:04Z"},
{"item_id":174,"name":"carrot","category":"Fashion","Warehouse":"WH1","stock_level":144,"last_update":"2025-06-18T06:00:37Z"},
{"item_id":175,"name":"pear","category":"Toys","Warehouse":"WH4","stock_level":200,"last_update":"2025-06-05T03:44:56Z"},
{"item_id":176,"name":"black-eyed pea","category":"Sweets","Warehouse":"WH5","stock_level":344,"last_update":"2025-06-13T00:06:31Z"},
{"item_id":177,"name":"avocado","category":"Vegetables","Warehouse":"WH4","stock_level":7,"last_update":"2025-06-29T07:50:55Z"},
{"item_id":178,"name":"dragonfruit","category":"Groceries","Warehouse":"WH1","stock_level":75,"last_update":"2025-06-06T11:42:31Z"},
{"item_id":179,"name":"sweets","category":"Electronic Items","Warehouse":"WH5","stock_level":36,"last_update":"2025-06-06T19:14:21Z"},
{"item_id":180,"name":"fava bean","category":"Toys","Warehouse":"WH2","stock_level":415,"last_update":"2025-06-07T13:01:46Z"},
{"item_id":181,"name":"onion","category":"Fruits","Warehouse":"WH5","stock_level":156,"last_update":"2025-06-11T23:06:02Z"},
{"item_id":182,"name":"split pea","category":"Fruits","Warehouse":"WH5","stock_level":185,"last_update":"2025-06-12T17:55:13Z"},
{"item_id":183,"name":"pistachio","category":"Fruits","Warehouse":"WH1","stock_level":131,"last_update":"2025-06-16T04:45:59Z"},
{"item_id":184,"name":"pistachio","category":"Packaged food","Warehouse":"WH4","stock_level":144,"last_update":"2025-06-18T18:50:01Z"},
{"item_id":185,"name":"coconut","category":"Fruits","Warehouse":"WH2","stock_level":283,"last_update":"2025-06-27T15:00:05Z"},
{"item_id":186,"name":"basil","category":"Packaged food","Warehouse":"WH3","stock_level":177,"last_update":"2025-06-14T04:39:51Z"},
{"item_id":187,"name":"walnut","category":"Sweets","Warehouse":"WH3","stock_level":216,"last_update":"2025-06-17T12:53:31Z"},
{"item_id":188,"name":"cumin","category":"Fruits","Warehouse":"WH4","stock_level":361,"last_update":"2025-06-29T09:09:08Z"},
{"item_id":189,"name":"adzuki bean","category":"Vegetables","Warehouse":"WH5","stock_level":199,"last_update":"2025-06-23T00:34:36Z"},
{"item_id":190,"name":"sweets","category":"Ice creams","Warehouse":"WH5","stock_level":384,"last_update":"2025-06-19T03:14:44Z"},
{"item_id":191,"name":"lettuce","category":"Vegetables","Warehouse":"WH5","stock_level":108,"last_update":"2025-06-11T18:24:44Z"},
{"item_id":192,"name":"bell pepper","category":"Toys","Warehouse":"WH4","stock_level":3,"last_update":"2025-06-28T22:01:55Z"},
{"item_id":193,"name":"barley","category":"Toys","Warehouse":"WH1","stock_level":176,"last_update":"2025-06-18T12:01:18Z"},
{"item_id":194,"name":"coconut","category":"Electronic Items","Warehouse":"WH2","stock_level":359,"last_update":"2025-06-14T08:04:27Z"},
{"item_id":195,"name":"kidney bean","category":"Fashion","Warehouse":"WH2","stock_level":63,"last_update":"2025-06-11T03:54:51Z"},
{"item_id":196,"name":"watermelon","category":"Electronic Items","Warehouse":"WH1","stock_level":357,"last_update":"2025-06-16T05:37:00Z"},
{"item_id":197,"name":"basil","category":"Dry fruits","Warehouse":"WH2","stock_level":18,"last_update":"2025-06-24T15:09:41Z"},
{"item_id":198,"name":"jackfruit","category":"Ice creams","Warehouse":"WH5","stock_level":444,"last_update":"2025-06-29T04:12:19Z"},
{"item_id":199,"name":"breadfruit","category":"Dry fruits","Warehouse":"WH1","stock_level":217,"last_update":"2025-06-29T14:49:59Z"},
{"item_id":200,"name":"cherry","category":"Groceries","Warehouse":"WH5","stock_level":245,"last_update":"2025-06-13T20:17:41Z"},
{"item_id":201,"name":"farro","category":"Electronic Items","Warehouse":"WH3","stock_level":46,"last_update":"2025-06-12T13:25:57Z"},
{"item_id":202,"name":"fig","category":"Electronic Items","Warehouse":"WH2","stock_level":42,"last_update":"2025-06-17T03:41:18Z"},
{"item_id":203,"name":"pomegranate","category":"Electronic Items","Warehouse":"WH5","stock_level":166,"last_update":"2025-06-16T19:03:07Z"},
{"item_id":204,"name":"cilantro","category":"Toys","Warehouse":"WH4","stock_level":33,"last_update":"2025-06-04T00:34:28Z"},
{"item_id":205,"name":"pinto bean","category":"Ice creams","Warehouse":"WH4","stock_level":179,"last_update":"2025-06-24T07:20:10Z"},
{"item_id":206,"name":"peach","category":"Packaged food","Warehouse":"WH4","stock_level":262,"last_update":"2025-06-23T01:45:14Z"},
{"item_id":207,"name":"oregano","category":"Toys","Warehouse":"WH1","stock_level":396,"last_update":"2025-06-27T09:18:33Z"},
{"item_id":208,"name":"garlic","category":"Ice creams","Warehouse":"WH1","stock_level":17,"last_update":"2025-06-24T20:53:47Z"},
{"item_id":209,"name":"walnut","category":"Toys","Warehouse":"WH5","stock_level":470,"last_update":"2025-06-10T03:20:50Z"},
{"item_id":210,"name":"eggplant","category":"Packaged food","Warehouse":"WH2","stock_level":367,"last_update":"2025-06-11T04:43:29Z"},
{"item_id":211,"name":"rye","category":"Packaged food","Warehouse":"WH3","stock_level":53,"last_update":"2025-06-13T23:53:05Z"},
{"item_id":212,"name":"dry fruits","category":"Dry fruits","Warehouse":"WH2","stock_level":388,"last_update":"2025-06-17T21:51:25Z"},
{"item_id":213,"name":"bulgur","category":"Packaged food","Warehouse":"WH2","stock_level":321,"last_update":"2025-06-25T02:52:47Z"},
{"item_id":214,"name":"sweets","category":"Fruits","Warehouse":"WH4","stock_level":441,"last_update":"2025-06-17T10:27:59Z"},
{"item_id":215,"name":"fig","category":"Sweets","Warehouse":"WH1","stock_level":388,"last_update":"2025-06-22T02:53:19Z"},
{"item_id":216,"name":"amaranth","category":"Dry fruits","Warehouse":"WH1","stock_level":490,"last_update":"2025-06-22T12:50:08Z"},
{"item_id":217,"name":"rye","category":"Toys","Warehouse":"WH4","stock_level":481,"last_update":"2025-06-02T21:24:00Z"},
{"item_id":218,"name":"ice creams","category":"Dry fruits","Warehouse":"WH5","stock_level":65,"last_update":"2025-06-10T03:10:37Z"},
{"item_id":219,"name":"farro","category":"Toys","Warehouse":"WH1","stock_level":166,"last_update":"2025-06-10T04:21:25Z"},
{"item_id":220,"name":"honeydew","category":"Dry fruits","Warehouse":"WH1","stock_level":115,"last_update":"2025-06-11T02:46:40Z"},
{"item_id":221,"name":"ginger","category":"Sweets","Warehouse":"WH2","stock_level":441,"last_update":"2025-06-22T10:22:59Z"},
{"item_id":222,"name":"cumin","category":"Fruits","Warehouse":"WH2","stock_level":290,"last_update":"2025-06-13T13:28:30Z"},
{"item_id":223,"name":"passionfruit","category":"Groceries","Warehouse":"WH2","stock_level":439,"last_update":"2025-06-15T16:40:15Z"},
{"item_id":224,"name":"plum","category":"Electronic Items","Warehouse":"WH1","stock_level":14,"last_update":"2025-06-17T22:52:14Z"},
{"item_id":225,"name":"lychee","category":"Vegetables","Warehouse":"WH5","stock_level":479,"last_update":"2025-06-05T11:50:48Z"},
{"item_id":226,"name":"jackfruit","category":"Groceries","Warehouse":"WH2","stock_level":355,"last_update":"2025-06-22T08:28:10Z"},
{"item_id":227,"name":"guava","category":"Fruits","Warehouse":"WH2","stock_level":147,"last_update":"2025-06-28T00:24:48Z"},
{"item_id":228,"name":"farro","category":"Sweets","Warehouse":"WH1","stock_level":52,"last_update":"2025-06-09T12:32:40Z"},
{"item_id":229,"name":"chickpea","category":"Ice creams","Warehouse":"WH2","stock_level":426,"last_update":"2025-06-08T22:05:53Z"},
{"item_id":230,"name":"sweet potato","category":"Sweets","Warehouse":"WH3","stock_level":364,"last_update":"2025-06-07T02:31:14Z"},
{"item_id":231,"name":"couscous","category":"Vegetables","Warehouse":"WH2","stock_level":343,"last_update":"2025-06-21T07:02:51Z"},
{"item_id":232,"name":"ginger","category":"Fruits","Warehouse":"WH1","stock_level":255,"last_update":"2025-06-13T01:10:07Z"},
{"item_id":233,"name":"jackfruit","category":"Packaged food","Warehouse":"WH5","stock_level":134,"last_update":"2025-06-05T16:53:37Z"},
{"item_id":234,"name":"cashew","category":"Ice creams","Warehouse":"WH1","stock_level":309,"last_update":"2025-06-01T03:29:29Z"},
{"item_id":235,"name":"amaranth","category":"Dry fruits","Warehouse":"WH5","stock_level":63,"last_update":"2025-06-23T22:57:30Z"},
{"item_id":236,"name":"raspberry","category":"Electronic Items","Warehouse":"WH5","stock_level":62,"last_update":"2025-06-18T06:41:48Z"},
{"item_id":237,"name":"eggplant","category":"Fashion","Warehouse":"WH3","stock_level":478,"last_update":"2025-06-07T03:24:01Z"},
{"item_id":238,"name":"kidney bean","category":"Electronic Items","Warehouse":"WH2","stock_level":476,"last_update":"2025-06-04T16:02:59Z"},
{"item_id":239,"name":"bulgur","category":"Vegetables","Warehouse":"WH4","stock_level":51,"last_update":"2025-06-17T00:54:12Z"},
{"item_id":240,"name":"lemon","category":"Vegetables","Warehouse":"WH2","stock_level":421,"last_update":"2025-06-18T19:40:50Z"},
{"item_id":241,"name":"garlic","category":"Dry fruits","Warehouse":"WH1","stock_level":49,"last_update":"2025-06-16T04:59:23Z"},
{"item_id":242,"name":"macadamia","category":"Vegetables","Warehouse":"WH1","stock_level":4,"last_update":"2025-06-18T09:22:22Z"},
{"item_id":243,"name":"sage","category":"Groceries","Warehouse":"WH3","stock_level":162,"last_update":"2025-06-06T23:40:22Z"},
{"item_id":244,"name":"tomato","category":"Electronic Items","Warehouse":"WH2","stock_level":151,"last_update":"2025-06-07T15:14:54Z"},
{"item_id":245,"name":"flaxseed","category":"Sweets","Warehouse":"WH4","stock_level":480,"last_update":"2025-06-23T00:16:12Z"},
{"item_id":246,"name":"cauliflower","category":"Fruits","Warehouse":"WH3","stock_level":178,"last_update":"2025-06-07T17:04:36Z"},
{"item_id":247,"name":"cucumber","category":"Toys","Warehouse":"WH4","stock_level":352,"last_update":"2025-06-27T07:06:14Z"},
{"item_id":248,"name":"cashew","category":"Sweets","Warehouse":"WH1","stock_level":348,"last_update":"2025-06-05T00:59:24Z"},
{"item_id":249,"name":"lychee","category":"Ice creams","Warehouse":"WH1","stock_level":431,"last_update":"2025-06-06T13:31:39Z"},
{"item_id":250,"name":"fig","category":"Sweets","Warehouse":"WH2","stock_level":308,"last_update":"2025-06-07T11:43:33Z"},
{"item_id":251,"name":"nutmeg","category":"Packaged food","Warehouse":"WH4","stock_level":41,"last_update":"2025-06-20T11:04:00Z"},
{"item_id":252,"name":"toys","category":"Packaged food","Warehouse":"WH1","stock_level":176,"last_update":"2025-06-20T11:08:48Z"},
{"item_id":253,"name":"turmeric","category":"Sweets","Warehouse":"WH3","stock_level":58,"last_update":"2025-06-24T22:47:01Z"},
{"item_id":254,"name":"turmeric","category":"Electronic Items","Warehouse":"WH2","stock_level":437,"last_update":"2025-06-12T17:57:56Z"},
{"item_id":255,"name":"nutmeg","category":"Ice creams","Warehouse":"WH4","stock_level":387,"last_update":"2025-06-29T04:33:47Z"},
{"item_id":256,"name":"pear","category":"Dry fruits","Warehouse":"WH3","stock_level":215,"last_update":"2025-06-08T08:46:14Z"},
{"item_id":257,"name":"walnut","category":"Fruits","Warehouse":"WH3","stock_level":244,"last_update":"2025-06-13T19:41:20Z"},
{"item_id":258,"name":"cantaloupe","category":"Sweets","Warehouse":"WH3","stock_level":360,"last_update":"2025-06-11T20:49:06Z"},
{"item_id":259,"name":"broccoli","category":"Fashion","Warehouse":"WH4","stock_level":146,"last_update":"2025-06-27T21:47:11Z"},
{"item_id":260,"name":"fig","category":"Dry fruits","Warehouse":"WH5","stock_level":494,"last_update":"2025-06-28T03:56:39Z"},
{"item_id":261,"name":"sunflower seed","category":"Sweets","Warehouse":"WH5","stock_level":259,"last_update":"2025-06-10T19:08:48Z"},
{"item_id":262,"name":"cinnamon","category":"Toys","Warehouse":"WH3","stock_level":61,"last_update":"2025-06-14T13:51:41Z"},
{"item_id":263,"name":"pineapple","category":"Packaged food","Warehouse":"WH2","stock_level":128,"last_update":"2025-06-13T04:35:18Z"},
{"item_id":264,"name":"honeydew","category":"Sweets","Warehouse":"WH3","stock_level":18,"last_update":"2025-06-01T04:28:03Z"},
{"item_id":265,"name":"chia seed","category":"Sweets","Warehouse":"WH3","stock_level":446,"last_update":"2025-06-18T17:15:39Z"},
{"item_id":266,"name":"strawberry","category":"Toys","Warehouse":"WH2","stock_level":102,"last_update":"2025-06-14T14:14:21Z"},
{"item_id":267,"name":"watermelon","category":"Vegetables","Warehouse":"WH2","stock_level":391,"last_update":"2025-06-06T09:40:25Z"},
{"item_id":268,"name":"turmeric","category":"Ice creams","Warehouse":"WH3","stock_level":404,"last_update":"2025-06-23T17:08:49Z"},
{"item_id":269,"name":"cilantro","category":"Fruits","Warehouse":"WH1","stock_level":454,"last_update":"2025-06-22T23:57:58Z"},
{"item_id":270,"name":"raspberry","category":"Vegetables","Warehouse":"WH3","stock_level":90,"last_update":"2025-06-29T07:43:12Z"},
{"item_id":271,"name":"pinto bean","category":"Fruits","Warehouse":"WH5","stock_level":302,"last_update":"2025-06-17T20:48:03Z"},
{"item_id":272,"name":"watermelon","category":"Packaged food","Warehouse":"WH3","stock_level":241,"last_update":"2025-06-06T02:45:20Z"},
{"item_id":273,"name":"chia seed","category":"Fashion","Warehouse":"WH5","stock_level":350,"last_update":"2025-06-25T00:01:31Z"},
{"item_id":274,"name":"pomegranate","category":"Fruits","Warehouse":"WH4","stock_level":148,"last_update":"2025-06-02T07:08:54Z"},
{"item_id":275,"name":"coconut","category":"Fashion","Warehouse":"WH1","stock_level":363,"last_update":"2025-06-12T05:07:25Z"},
{"item_id":276,"name":"soybean","category":"Electronic Items","Warehouse":"WH2","stock_level":326,"last_update":"2025-06-12T04:08:50Z"},
{"item_id":277,"name":"electronic items","category":"Dry fruits","Warehouse":"WH4","stock_level":13,"last_update":"2025-06-15T08:40:19Z"},
{"item_id":278,"name":"cashew","category":"Vegetables","Warehouse":"WH1","stock_level":410,"last_update":"2025-06-20T04:57:50Z"},
{"item_id":279,"name":"pecan","category":"Electronic Items","Warehouse":"WH2","stock_level":356,"last_update":"2025-06-22T08:03:35Z"},
{"item_id":280,"name":"sesame seed","category":"Toys","Warehouse":"WH1","stock_level":484,"last_update":"2025-06-28T08:20:31Z"},
{"item_id":281,"name":"passionfruit","category":"Toys","Warehouse":"WH2","stock_level":442,"last_update":"2025-06-15T21:59:33Z"},
{"item_id":282,"name":"cabbage","category":"Sweets","Warehouse":"WH2","stock_level":416,"last_update":"2025-06-19T21:20:17Z"},
{"item_id":283,"name":"navy bean","category":"Vegetables","Warehouse":"WH4","stock_level":404,"last_update":"2025-06-06T09:39:23Z"},
{"item_id":284,"name":"mint","category":"Packaged food","Warehouse":"WH3","stock_level":319,"last_update":"2025-06-23T02:05:49Z"},
{"item_id":285,"name":"mangosteen","category":"Toys","Warehouse":"WH4","stock_level":123,"last_update":"2025-06-06T05:06:31Z"},
{"item_id":286,"name":"black-eyed pea","category":"Ice creams","Warehouse":"WH2","stock_level":106,"last_update":"2025-06-27T04:11:57Z"},
{"item_id":287,"name":"plantain","category":"Fashion","Warehouse":"WH1","stock_level":387,"last_update":"2025-06-19T04:22:11Z"},
{"item_id":288,"name":"adzuki bean","category":"Ice creams","Warehouse":"WH4","stock_level":247,"last_update":"2025-06-06T06:16:10Z"},
{"item_id":289,"name":"mint","category":"Groceries","Warehouse":"WH4","stock_level":190,"last_update":"2025-06-25T08:09:15Z"},
{"item_id":290,"name":"black bean","category":"Ice creams","Warehouse":"WH1","stock_level":84,"last_update":"2025-06-06T22:43:42Z"},
{"item_id":291,"name":"lychee","category":"Toys","Warehouse":"WH5","stock_level":321,"last_update":"2025-06-08T03:35:33Z"},
{"item_id":292,"name":"mango","category":"Fruits","Warehouse":"WH1","stock_level":242,"last_update":"2025-06-12T15:55:10Z"},
{"item_id":293,"name":"garlic","category":"Electronic Items","Warehouse":"WH4","stock_level":149,"last_update":"2025-06-11T18:17:58Z"},
{"item_id":294,"name":"sweet potato","category":"Packaged food","Warehouse":"WH1","stock_level":177,"last_update":"2025-06-22T20:31:21Z"},
{"item_id":295,"name":"rye","category":"Vegetables","Warehouse":"WH5","stock_level":494,"last_update":"2025-06-14T19:11:22Z"},
{"item_id":296,"name":"pumpkin seed","category":"Groceries","Warehouse":"WH2","stock_level":47,"last_update":"2025-06-11T07:07:05Z"},
{"item_id":297,"name":"blackberry","category":"Sweets","Warehouse":"WH3","stock_level":231,"last_update":"2025-06-20T11:27:23Z"},
{"item_id":298,"name":"black-eyed pea","category":"Sweets","Warehouse":"WH2","stock_level":227,"last_update":"2025-06-26T01:36:18Z"},
{"item_id":299,"name":"black bean","category":"Fruits","Warehouse":"WH5","stock_level":476,"last_update":"2025-06-02T20:55:20Z"},
{"item_id":300,"name":"dill","category":"Fashion","Warehouse":"WH1","stock_level":380,"last_update":"2025-06-03T14:50:49Z"},
{"item_id":301,"name":"buckwheat","category":"Toys","Warehouse":"WH4","stock_level":358,"last_update":"2025-06-16T21:58:21Z"},
{"item_id":302,"name":"bay leaf","category":"Sweets","Warehouse":"WH1","stock_level":54,"last_update":"2025-06-18T07:39:05Z"},
{"item_id":303,"name":"carrot","category":"Packaged food","Warehouse":"WH2","stock_level":51,"last_update":"2025-06-08T00:29:56Z"},
{"item_id":304,"name":"sweet potato","category":"Fashion","Warehouse":"WH1","stock_level":96,"last_update":"2025-06-24T04:58:02Z"},
{"item_id":305,"name":"pear","category":"Vegetables","Warehouse":"WH4","stock_level":138,"last_update":"2025-06-06T17:01:18Z"},
{"item_id":306,"name":"potato","category":"Packaged food","Warehouse":"WH2","stock_level":202,"last_update":"2025-06-29T12:43:44Z"},
{"item_id":307,"name":"rosemary","category":"Groceries","Warehouse":"WH5","stock_level":341,"last_update":"2025-06-24T05:34:00Z"},
{"item_id":308,"name":"ginger","category":"Electronic Items","Warehouse":"WH4","stock_level":198,"last_update":"2025-06-12T06:00:26Z"},
{"item_id":309,"name":"raspberry","category":"Fashion","Warehouse":"WH5","stock_level":480,"last_update":"2025-06-27T10:36:36Z"},
{"item_id":310,"name":"peanut","category":"Toys","Warehouse":"WH3","stock_level":406,"last_update":"2025-06-19T20:13:18Z"},
{"item_id":311,"name":"chives","category":"Electronic Items","Warehouse":"WH1","stock_level":448,"last_update":"2025-06-15T17:36:27Z"},
{"item_id":312,"name":"cilantro","category":"Ice creams","Warehouse":"WH2","stock_level":223,"last_update":"2025-06-08T22:16:26Z"},
{"item_id":313,"name":"spinach","category":"Electronic Items","Warehouse":"WH4","stock_level":371,"last_update":"2025-06-03T14:52:09Z"},
{"item_id":314,"name":"lychee","category":"Fashion","Warehouse":"WH5","stock_level":328,"last_update":"2025-06-21T01:29:53Z"},
{"item_id":315,"name":"dill","category":"Fashion","Warehouse":"WH5","stock_level":442,"last_update":"2025-06-22T21:02:28Z"},
{"item_id":316,"name":"plantain","category":"Electronic Items","Warehouse":"WH2","stock_level":460,"last_update":"2025-06-23T06:08:38Z"},
{"item_id":317,"name":"kale","category":"Fruits","Warehouse":"WH1","stock_level":380,"last_update":"2025-06-20T08:44:25Z"},
{"item_id":318,"name":"carrot","category":"Toys","Warehouse":"WH3","stock_level":214,"last_update":"2025-06-20T08:22:32Z"},
{"item_id":319,"name":"oregano","category":"Toys","Warehouse":"WH4","stock_level":220,"last_update":"2025-06-08T17:20:11Z"},
{"item_id":320,"name":"turmeric","category":"Toys","Warehouse":"WH2","stock_level":171,"last_update":"2025-06-07T20:48:05Z"},
{"item_id":321,"name":"turmeric","category":"Fashion","Warehouse":"WH5","stock_level":490,"last_update":"2025-06-28T16:34:14Z"},
{"item_id":322,"name":"lettuce","category":"Fruits","Warehouse":"WH3","stock_level":214,"last_update":"2025-06-27T08:29:25Z"},
{"item_id":323,"name":"coconut","category":"Fashion","Warehouse":"WH2","stock_level":336,"last_update":"2025-06-17T14:29:23Z"},
{"item_id":324,"name":"spinach","category":"Dry fruits","Warehouse":"WH3","stock_level":466,"last_update":"2025-06-13T03:56:19Z"},
{"item_id":325,"name":"walnut","category":"Fashion","Warehouse":"WH5","stock_level":468,"last_update":"2025-06-14T07:26:43Z"},
{"item_id":326,"name":"carrot","category":"Electronic Items","Warehouse":"WH4","stock_level":134,"last_update":"2025-06-25T08:07:05Z"},
{"item_id":327,"name":"blackberry","category":"Sweets","Warehouse":"WH2","stock_level":474,"last_update":"2025-06-04T13:00:20Z"},
{"item_id":328,"name":"rice","category":"Vegetables","Warehouse":"WH4","stock_level":48,"last_update":"2025-06-16T06:16:58Z"},
{"item_id":329,"name":"peanut","category":"Ice creams","Warehouse":"WH1","stock_level":298,"last_update":"2025-06-19T17:33:12Z"},
{"item_id":330,"name":"apricot","category":"Packaged food","Warehouse":"WH5","stock_level":219,"last_update":"2025-06-06T18:16:43Z"},
{"item_id":331,"name":"peanut","category":"Groceries","Warehouse":"WH3","stock_level":371,"last_update":"2025-06-26T02:03:17Z"},
{"item_id":332,"name":"starfruit","category":"Electronic Items","Warehouse":"WH2","stock_level":84,"last_update":"2025-06-17T15:17:11Z"},
{"item_id":333,"name":"lima bean","category":"Groceries","Warehouse":"WH1","stock_level":19,"last_update":"2025-06-21T22:46:28Z"},
{"item_id":334,"name":"banana","category":"Sweets","Warehouse":"WH1","stock_level":388,"last_update":"2025-06-21T06:27:46Z"},
{"item_id":335,"name":"corn","category":"Fashion","Warehouse":"WH2","stock_level":408,"last_update":"2025-06-04T00:52:13Z"},
{"item_id":336,"name":"cucumber","category":"Toys","Warehouse":"WH4","stock_level":92,"last_update":"2025-06-06T12:34:26Z"},
{"item_id":337,"name":"turmeric","category":"Toys","Warehouse":"WH2","stock_level":109,"last_update":"2025-06-07T22:19:52Z"},
{"item_id":338,"name":"rice","category":"Packaged food","Warehouse":"WH4","stock_level":157,"last_update":"2025-06-05T16:34:38Z"},
{"item_id":339,"name":"raspberry","category":"Dry fruits","Warehouse":"WH3","stock_level":290,"last_update":"2025-06-08T22:57:43Z"},
{"item_id":340,"name":"paprika","category":"Fruits","Warehouse":"WH3","stock_level":393,"last_update":"2025-06-21T22:50:18Z"},
{"item_id":341,"name":"black-eyed pea","category":"Fruits","Warehouse":"WH5","stock_level":162,"last_update":"2025-06-27T11:09:17Z"},
{"item_id":342,"name":"bell pepper","category":"Dry fruits","Warehouse":"WH2","stock_level":49,"last_update":"2025-06-29T03:25:28Z"},
{"item_id":343,"name":"walnut","category":"Sweets","Warehouse":"WH3","stock_level":363,"last_update":"2025-06-24T21:24:46Z"},
{"item_id":344,"name":"raspberry","category":"Packaged food","Warehouse":"WH3","stock_level":395,"last_update":"2025-06-12T11:55:15Z"},
{"item_id":345,"name":"cinnamon","category":"Toys","Warehouse":"WH3","stock_level":320,"last_update":"2025-06-20T14:25:19Z"},
{"item_id":346,"name":"cantaloupe","category":"Groceries","Warehouse":"WH1","stock_level":271,"last_update":"2025-06-10T20:31:55Z"},
{"item_id":347,"name":"sunflower seed","category":"Groceries","Warehouse":"WH2","stock_level":87,"last_update":"2025-06-06T12:56:05Z"},
{"item_id":348,"name":"ginger","category":"Vegetables","Warehouse":"WH3","stock_level":314,"last_update":"2025-06-26T22:55:05Z"},
{"item_id":349,"name":"lentil","category":"Electronic Items","Warehouse":"WH1","stock_level":350,"last_update":"2025-06-17T13:09:35Z"},
{"item_id":350,"name":"dill","category":"Vegetables","Warehouse":"WH2","stock_level":70,"last_update":"2025-06-24T20:31:43Z"},
{"item_id":351,"name":"fig","category":"Fashion","Warehouse":"WH2","stock_level":462,"last_update":"2025-06-16T20:23:59Z"},
{"item_id":352,"name":"guava","category":"Electronic Items","Warehouse":"WH1","stock_level":468,"last_update":"2025-06-03T18:54:17Z"},
{"item_id":353,"name":"cashew","category":"Vegetables","Warehouse":"WH2","stock_level":310,"last_update":"2025-06-15T14:39:15Z"},
{"item_id":354,"name":"grape","category":"Groceries","Warehouse":"WH4","stock_level":141,"last_update":"2025-06-27T20:03:21Z"},
{"item_id":355,"name":"barley","category":"Packaged food","Warehouse":"WH2","stock_level":18,"last_update":"2025-06-21T08:34:52Z"},
{"item_id":356,"name":"mustard","category":"Electronic Items","Warehouse":"WH4","stock_level":425,"last_update":"2025-06-17T10:51:55Z"},
{"item_id":357,"name":"orange","category":"Sweets","Warehouse":"WH4","stock_level":407,"last_update":"2025-06-14T03:36:16Z"},
{"item_id":358,"name":"mung bean","category":"Dry fruits","Warehouse":"WH5","stock_level":499,"last_update":"2025-06-15T21:09:03Z"},
{"item_id":359,"name":"lima bean","category":"Ice creams","Warehouse":"WH5","stock_level":484,"last_update":"2025-06-06T23:17:05Z"},
{"item_id":360,"name":"cumin","category":"Packaged food","Warehouse":"WH1","stock_level":290,"last_update":"2025-06-19T17:40:37Z"},
{"item_id":361,"name":"packaged food","category":"Electronic Items","Warehouse":"WH4","stock_level":390,"last_update":"2025-06-04T21:51:32Z"},
{"item_id":362,"name":"packaged food","category":"Sweets","Warehouse":"WH3","stock_level":8,"last_update":"2025-06-10T04:27:55Z"},
{"item_id":363,"name":"broccoli","category":"Fashion","Warehouse":"WH3","stock_level":370,"last_update":"2025-06-12T22:31:39Z"},
{"item_id":364,"name":"mung bean","category":"Packaged food","Warehouse":"WH1","stock_level":463,"last_update":"2025-06-09T09:40:14Z"},
{"item_id":365,"name":"cucumber","category":"Sweets","Warehouse":"WH1","stock_level":432,"last_update":"2025-06-27T19:38:37Z"},
{"item_id":366,"name":"onion","category":"Ice creams","Warehouse":"WH2","stock_level":446,"last_update":"2025-06-08T13:55:17Z"},
{"item_id":367,"name":"toys","category":"Groceries","Warehouse":"WH1","stock_level":238,"last_update":"2025-06-18T20:02:53Z"},
{"item_id":368,"name":"plum","category":"Vegetables","Warehouse":"WH4","stock_level":130,"last_update":"2025-06-25T10:02:18Z"},
{"item_id":369,"name":"couscous","category":"Groceries","Warehouse":"WH5","stock_level":246,"last_update":"2025-06-05T03:31:36Z"},
{"item_id":370,"name":"almond","category":"Electronic Items","Warehouse":"WH5","stock_level":331,"last_update":"2025-06-05T18:53:58Z"},
{"item_id":371,"name":"strawberry","category":"Ice creams","Warehouse":"WH4","stock_level":346,"last_update":"2025-06-05T16:10:45Z"},
{"item_id":372,"name":"amaranth","category":"Groceries","Warehouse":"WH1","stock_level":80,"last_update":"2025-06-01T04:15:06Z"},
{"item_id":373,"name":"green pea","category":"Vegetables","Warehouse":"WH5","stock_level":297,"last_update":"2025-06-20T05:06:38Z"},
{"item_id":374,"name":"garlic","category":"Ice creams","Warehouse":"WH4","stock_level":316,"last_update":"2025-06-17T04:07:03Z"},
{"item_id":375,"name":"walnut","category":"Vegetables","Warehouse":"WH3","stock_level":365,"last_update":"2025-06-01T03:27:34Z"},
{"item_id":376,"name":"cilantro","category":"Groceries","Warehouse":"WH2","stock_level":429,"last_update":"2025-06-03T00:31:03Z"},
{"item_id":377,"name":"chia seed","category":"Ice creams","Warehouse":"WH1","stock_level":439,"last_update":"2025-06-03T08:07:53Z"},
{"item_id":378,"name":"spelt","category":"Packaged food","Warehouse":"WH1","stock_level":5,"last_update":"2025-06-14T21:27:07Z"},
{"item_id":379,"name":"basil","category":"Groceries","Warehouse":"WH2","stock_level":344,"last_update":"2025-06-27T16:15:08Z"},
{"item_id":380,"name":"chia seed","category":"Fashion","Warehouse":"WH5","stock_level":250,"last_update":"2025-06-27T13:17:42Z"},
{"item_id":381,"name":"bulgur","category":"Vegetables","Warehouse":"WH3","stock_level":498,"last_update":"2025-06-08T03:32:02Z"},
{"item_id":382,"name":"rye","category":"Dry fruits","Warehouse":"WH3","stock_level":154,"last_update":"2025-06-07T14:30:59Z"},
{"item_id":383,"name":"buckwheat","category":"Sweets","Warehouse":"WH1","stock_level":411,"last_update":"2025-06-17T08:28:41Z"},
{"item_id":384,"name":"walnut","category":"Fruits","Warehouse":"WH2","stock_level":472,"last_update":"2025-06-02T18:58:09Z"},
{"item_id":385,"name":"avocado","category":"Ice creams","Warehouse":"WH3","stock_level":214,"last_update":"2025-06-18T12:26:37Z"},
{"item_id":386,"name":"mangosteen","category":"Fashion","Warehouse":"WH5","stock_level":421,"last_update":"2025-06-26T09:58:39Z"},
{"item_id":387,"name":"sunflower seed","category":"Fruits","Warehouse":"WH2","stock_level":415,"last_update":"2025-06-10T00:57:47Z"},
{"item_id":388,"name":"chia seed","category":"Dry fruits","Warehouse":"WH1","stock_level":143,"last_update":"2025-06-29T19:47:30Z"},
{"item_id":389,"name":"peanut","category":"Dry fruits","Warehouse":"WH5","stock_level":494,"last_update":"2025-06-22T00:58:04Z"},
{"item_id":390,"name":"papaya","category":"Toys","Warehouse":"WH5","stock_level":28,"last_update":"2025-06-08T02:59:33Z"},
{"item_id":391,"name":"strawberry","category":"Dry fruits","Warehouse":"WH5","stock_level":353,"last_update":"2025-06-12T03:10:30Z"},
{"item_id":392,"name":"macadamia","category":"Packaged food","Warehouse":"WH3","stock_level":448,"last_update":"2025-06-24T10:38:25Z"},
{"item_id":393,"name":"guava","category":"Dry fruits","Warehouse":"WH1","stock_level":151,"last_update":"2025-06-25T06:52:22Z"},
{"item_id":394,"name":"spelt","category":"Vegetables","Warehouse":"WH3","stock_level":456,"last_update":"2025-06-18T06:19:18Z"},
{"item_id":395,"name":"apple","category":"Electronic Items","Warehouse":"WH1","stock_level":378,"last_update":"2025-06-14T11:15:51Z"},
{"item_id":396,"name":"dill","category":"Ice creams","Warehouse":"WH1","stock_level":4,"last_update":"2025-06-20T19:11:30Z"},
{"item_id":397,"name":"eggplant","category":"Dry fruits","Warehouse":"WH4","stock_level":101,"last_update":"2025-06-21T21:15:30Z"},
{"item_id":398,"name":"lentil","category":"Fruits","Warehouse":"WH1","stock_level":265,"last_update":"2025-06-23T20:03:18Z"},
{"item_id":399,"name":"sweet potato","category":"Electronic Items","Warehouse":"WH4","stock_level":57,"last_update":"2025-06-10T19:01:37Z"},
{"item_id":400,"name":"paprika","category":"Vegetables","Warehouse":"WH5","stock_level":15,"last_update":"2025-06-28T00:13:52Z"},
{"item_id":401,"name":"ginger","category":"Fashion","Warehouse":"WH2","stock_level":364,"last_update":"2025-06-18T10:39:25Z"},
{"item_id":402,"name":"strawberry","category":"Ice creams","Warehouse":"WH1","stock_level":54,"last_update":"2025-06-13T17:06:28Z"},
{"item_id":403,"name":"wheat","category":"Electronic Items","Warehouse":"WH5","stock_level":163,"last_update":"2025-06-15T23:41:17Z"},
{"item_id":404,"name":"mango","category":"Sweets","Warehouse":"WH5","stock_level":103,"last_update":"2025-06-15T05:26:50Z"},
{"item_id":405,"name":"sweet potato","category":"Packaged food","Warehouse":"WH3","stock_level":151,"last_update":"2025-06-15T22:30:39Z"},
{"item_id":406,"name":"oats","category":"Groceries","Warehouse":"WH1","stock_level":393,"last_update":"2025-06-29T15:48:14Z"},
{"item_id":407,"name":"breadfruit","category":"Groceries","Warehouse":"WH2","stock_level":192,"last_update":"2025-06-19T20:16:54Z"},
{"item_id":408,"name":"lychee","category":"Dry fruits","Warehouse":"WH2","stock_level":124,"last_update":"2025-06-01T07:59:32Z"},
{"item_id":409,"name":"thyme","category":"Vegetables","Warehouse":"WH5","stock_level":430,"last_update":"2025-06-20T08:32:58Z"},
{"item_id":410,"name":"blackberry","category":"Ice creams","Warehouse":"WH4","stock_level":67,"last_update":"2025-06-22T10:09:20Z"},
{"item_id":411,"name":"flaxseed","category":"Sweets","Warehouse":"WH1","stock_level":173,"last_update":"2025-06-13T12:45:29Z"},
{"item_id":412,"name":"kale","category":"Electronic Items","Warehouse":"WH2","stock_level":282,"last_update":"2025-06-06T01:48:40Z"},
{"item_id":413,"name":"packaged food","category":"Dry fruits","Warehouse":"WH2","stock_level":213,"last_update":"2025-06-27T17:55:05Z"},
{"item_id":414,"name":"almond","category":"Packaged food","Warehouse":"WH5","stock_level":368,"last_update":"2025-06-25T16:33:24Z"},
{"item_id":415,"name":"farro","category":"Fruits","Warehouse":"WH4","stock_level":177,"last_update":"2025-06-12T04:13:53Z"},
{"item_id":416,"name":"green pea","category":"Vegetables","Warehouse":"WH3","stock_level":123,"last_update":"2025-06-09T05:00:37Z"},
{"item_id":417,"name":"adzuki bean","category":"Vegetables","Warehouse":"WH2","stock_level":110,"last_update":"2025-06-25T21:58:08Z"},
{"item_id":418,"name":"mint","category":"Electronic Items","Warehouse":"WH4","stock_level":38,"last_update":"2025-06-01T18:39:02Z"},
{"item_id":419,"name":"onion","category":"Electronic Items","Warehouse":"WH1","stock_level":166,"last_update":"2025-06-22T19:21:43Z"},
{"item_id":420,"name":"grape","category":"Fashion","Warehouse":"WH1","stock_level":380,"last_update":"2025-06-19T08:28:34Z"},
{"item_id":421,"name":"cilantro","category":"Ice creams","Warehouse":"WH4","stock_level":154,"last_update":"2025-06-10T00:20:50Z"},
{"item_id":422,"name":"cumin","category":"Packaged food","Warehouse":"WH2","stock_level":240,"last_update":"2025-06-14T08:19:58Z"},
{"item_id":423,"name":"barley","category":"Dry fruits","Warehouse":"WH3","stock_level":10,"last_update":"2025-06-29T06:41:50Z"},
{"item_id":424,"name":"pomegranate","category":"Electronic Items","Warehouse":"WH4","stock_level":222,"last_update":"2025-06-18T18:16:24Z"},
{"item_id":425,"name":"packaged food","category":"Vegetables","Warehouse":"WH4","stock_level":123,"last_update":"2025-06-29T19:32:45Z"},
{"item_id":426,"name":"sage","category":"Ice creams","Warehouse":"WH3","stock_level":30,"last_update":"2025-06-07T18:26:07Z"},
{"item_id":427,"name":"couscous","category":"Fashion","Warehouse":"WH2","stock_level":488,"last_update":"2025-06-13T03:02:07Z"},
{"item_id":428,"name":"pinto bean","category":"Dry fruits","Warehouse":"WH2","stock_level":475,"last_update":"2025-06-29T05:28:41Z"},
{"item_id":429,"name":"cashew","category":"Packaged food","Warehouse":"WH3","stock_level":76,"last_update":"2025-06-29T21:32:16Z"},
{"item_id":430,"name":"zucchini","category":"Electronic Items","Warehouse":"WH5","stock_level":251,"last_update":"2025-06-06T19:32:46Z"},
{"item_id":431,"name":"parsley","category":"Groceries","Warehouse":"WH2","stock_level":462,"last_update":"2025-06-20T02:45:24Z"},
{"item_id":432,"name":"lima bean","category":"Sweets","Warehouse":"WH4","stock_level":163,"last_update":"2025-06-02T17:15:32Z"},
{"item_id":433,"name":"peanut","category":"Fruits","Warehouse":"WH4","stock_level":28,"last_update":"2025-06-01T08:48:40Z"},
{"item_id":434,"name":"mung bean","category":"Fruits","Warehouse":"WH2","stock_level":66,"last_update":"2025-06-23T15:03:12Z"},
{"item_id":435,"name":"almond","category":"Packaged food","Warehouse":"WH5","stock_level":220,"last_update":"2025-06-19T13:30:50Z"},
{"item_id":436,"name":"papaya","category":"Vegetables","Warehouse":"WH4","stock_level":486,"last_update":"2025-06-16T04:45:54Z"},
{"item_id":437,"name":"wheat","category":"Fruits","Warehouse":"WH4","stock_level":42,"last_update":"2025-06-13T06:28:47Z"},
{"item_id":438,"name":"banana","category":"Groceries","Warehouse":"WH1","stock_level":204,"last_update":"2025-06-18T20:21:06Z"},
{"item_id":439,"name":"walnut","category":"Sweets","Warehouse":"WH4","stock_level":234,"last_update":"2025-06-19T22:33:18Z"},
{"item_id":440,"name":"honeydew","category":"Ice creams","Warehouse":"WH1","stock_level":177,"last_update":"2025-06-03T04:05:58Z"},
{"item_id":441,"name":"starfruit","category":"Ice creams","Warehouse":"WH4","stock_level":206,"last_update":"2025-06-08T00:43:15Z"},
{"item_id":442,"name":"papaya","category":"Toys","Warehouse":"WH1","stock_level":78,"last_update":"2025-06-17T15:51:12Z"},
{"item_id":443,"name":"chickpea","category":"Ice creams","Warehouse":"WH2","stock_level":279,"last_update":"2025-06-20T18:36:34Z"},
{"item_id":444,"name":"hazelnut","category":"Toys","Warehouse":"WH2","stock_level":193,"last_update":"2025-06-26T20:04:26Z"},
{"item_id":445,"name":"chives","category":"Dry fruits","Warehouse":"WH4","stock_level":440,"last_update":"2025-06-01T14:22:19Z"},
{"item_id":446,"name":"lychee","category":"Vegetables","Warehouse":"WH4","stock_level":378,"last_update":"2025-06-18T11:29:22Z"},
{"item_id":447,"name":"dry fruits","category":"Fruits","Warehouse":"WH3","stock_level":123,"last_update":"2025-06-27T20:50:36Z"},
{"item_id":448,"name":"pinto bean","category":"Sweets","Warehouse":"WH4","stock_level":320,"last_update":"2025-06-17T14:34:34Z"},
{"item_id":449,"name":"ginger","category":"Electronic Items","Warehouse":"WH3","stock_level":251,"last_update":"2025-06-15T07:12:33Z"},
{"item_id":450,"name":"mustard","category":"Dry fruits","Warehouse":"WH2","stock_level":370,"last_update":"2025-06-27T07:42:30Z"},
{"item_id":451,"name":"cinnamon","category":"Fruits","Warehouse":"WH5","stock_level":286,"last_update":"2025-06-09T16:38:08Z"},
{"item_id":452,"name":"vanilla","category":"Vegetables","Warehouse":"WH1","stock_level":9,"last_update":"2025-06-04T20:54:15Z"},
{"item_id":453,"name":"fava bean","category":"Dry fruits","Warehouse":"WH1","stock_level":465,"last_update":"2025-06-18T19:58:06Z"},
{"item_id":454,"name":"kale","category":"Fashion","Warehouse":"WH5","stock_level":28,"last_update":"2025-06-27T02:41:45Z"},
{"item_id":455,"name":"toys","category":"Packaged food","Warehouse":"WH4","stock_level":7,"last_update":"2025-06-19T02:19:54Z"},
{"item_id":456,"name":"sunflower seed","category":"Ice creams","Warehouse":"WH5","stock_level":455,"last_update":"2025-06-21T21:13:30Z"},
{"item_id":457,"name":"pear","category":"Sweets","Warehouse":"WH1","stock_level":482,"last_update":"2025-06-05T08:13:04Z"},
{"item_id":458,"name":"pistachio","category":"Dry fruits","Warehouse":"WH3","stock_level":272,"last_update":"2025-06-02T04:53:35Z"},
{"item_id":459,"name":"bulgur","category":"Fruits","Warehouse":"WH2","stock_level":149,"last_update":"2025-06-11T02:42:17Z"},
{"item_id":460,"name":"breadfruit","category":"Fruits","Warehouse":"WH2","stock_level":223,"last_update":"2025-06-09T06:05:05Z"},
{"item_id":461,"name":"navy bean","category":"Dry fruits","Warehouse":"WH3","stock_level":424,"last_update":"2025-06-12T17:42:00Z"},
{"item_id":462,"name":"mustard","category":"Toys","Warehouse":"WH2","stock_level":413,"last_update":"2025-06-02T15:23:02Z"},
{"item_id":463,"name":"millet","category":"Groceries","Warehouse":"WH2","stock_level":222,"last_update":"2025-06-17T09:45:14Z"},
{"item_id":464,"name":"orange","category":"Dry fruits","Warehouse":"WH1","stock_level":494,"last_update":"2025-06-05T07:14:09Z"},
{"item_id":465,"name":"walnut","category":"Groceries","Warehouse":"WH4","stock_level":446,"last_update":"2025-06-23T09:47:15Z"},
{"item_id":466,"name":"coconut","category":"Groceries","Warehouse":"WH3","stock_level":4,"last_update":"2025-06-21T20:34:31Z"},
{"item_id":467,"name":"guava","category":"Ice creams","Warehouse":"WH4","stock_level":61,"last_update":"2025-06-15T02:19:07Z"},
{"item_id":468,"name":"pineapple","category":"Packaged food","Warehouse":"WH4","stock_level":356,"last_update":"2025-06-15T00:25:00Z"},
{"item_id":469,"name":"sweet potato","category":"Packaged food","Warehouse":"WH1","stock_level":484,"last_update":"2025-06-28T04:40:14Z"},
{"item_id":470,"name":"coriander","category":"Toys","Warehouse":"WH4","stock_level":451,"last_update":"2025-06-12T23:21:06Z"},
{"item_id":471,"name":"pomegranate","category":"Toys","Warehouse":"WH4","stock_level":380,"last_update":"2025-06-03T09:20:50Z"},
{"item_id":472,"name":"cayenne","category":"Dry fruits","Warehouse":"WH5","stock_level":8,"last_update":"2025-06-18T00:14:41Z"},
{"item_id":473,"name":"millet","category":"Electronic Items","Warehouse":"WH3","stock_level":273,"last_update":"2025-06-05T07:35:05Z"},
{"item_id":474,"name":"mangosteen","category":"Fashion","Warehouse":"WH4","stock_level":104,"last_update":"2025-06-14T10:42:41Z"},
{"item_id":475,"name":"amaranth","category":"Ice creams","Warehouse":"WH2","stock_level":126,"last_update":"2025-06-26T12:40:53Z"},
{"item_id":476,"name":"plantain","category":"Groceries","Warehouse":"WH5","stock_level":494,"last_update":"2025-06-09T19:17:13Z"},
{"item_id":477,"name":"ice creams","category":"Electronic Items","Warehouse":"WH2","stock_level":16,"last_update":"2025-06-21T00:44:19Z"},
{"item_id":478,"name":"rye","category":"Electronic Items","Warehouse":"WH3","stock_level":102,"last_update":"2025-06-25T21:04:31Z"},
{"item_id":479,"name":"strawberry","category":"Sweets","Warehouse":"WH4","stock_level":41,"last_update":"2025-06-15T11:41:29Z"},
{"item_id":480,"name":"oats","category":"Packaged food","Warehouse":"WH4","stock_level":476,"last_update":"2025-06-14T22:16:13Z"},
{"item_id":481,"name":"thyme","category":"Vegetables","Warehouse":"WH5","stock_level":146,"last_update":"2025-06-16T05:38:32Z"},
{"item_id":482,"name":"oats","category":"Fruits","Warehouse":"WH5","stock_level":139,"last_update":"2025-06-03T09:07:25Z"},
{"item_id":483,"name":"raspberry","category":"Vegetables","Warehouse":"WH1","stock_level":72,"last_update":"2025-06-17T21:06:22Z"},
{"item_id":484,"name":"fava bean","category":"Fashion","Warehouse":"WH1","stock_level":391,"last_update":"2025-06-26T13:48:00Z"},
{"item_id":485,"name":"basil","category":"Toys","Warehouse":"WH1","stock_level":287,"last_update":"2025-06-29T20:00:02Z"},
{"item_id":486,"name":"lychee","category":"Dry fruits","Warehouse":"WH5","stock_level":287,"last_update":"2025-06-16T03:28:23Z"},
{"item_id":487,"name":"bell pepper","category":"Electronic Items","Warehouse":"WH4","stock_level":435,"last_update":"2025-06-19T00:06:04Z"},
{"item_id":488,"name":"dill","category":"Groceries","Warehouse":"WH4","stock_level":438,"last_update":"2025-06-25T19:47:08Z"},
{"item_id":489,"name":"watermelon","category":"Toys","Warehouse":"WH2","stock_level":497,"last_update":"2025-06-15T15:48:26Z"},
{"item_id":490,"name":"mangosteen","category":"Toys","Warehouse":"WH2","stock_level":34,"last_update":"2025-06-28T09:29:42Z"},
{"item_id":491,"name":"sweets","category":"Fashion","Warehouse":"WH4","stock_level":451,"last_update":"2025-06-24T14:00:14Z"},
{"item_id":492,"name":"bulgur","category":"Dry fruits","Warehouse":"WH1","stock_level":402,"last_update":"2025-06-16T09:16:01Z"},
{"item_id":493,"name":"cabbage","category":"Groceries","Warehouse":"WH2","stock_level":181,"last_update":"2025-06-26T20:52:01Z"},
{"item_id":494,"name":"kale","category":"Sweets","Warehouse":"WH1","stock_level":411,"last_update":"2025-06-19T09:07:35Z"},
{"item_id":495,"name":"sage","category":"Electronic Items","Warehouse":"WH4","stock_level":198,"last_update":"2025-06-12T20:25:32Z"},
{"item_id":496,"name":"soybean","category":"Vegetables","Warehouse":"WH2","stock_level":88,"last_update":"2025-06-12T12:16:13Z"},
{"item_id":497,"name":"paprika","category":"Fruits","Warehouse":"WH1","stock_level":262,"last_update":"2025-06-09T06:43:25Z"},
{"item_id":498,"name":"chickpea","category":"Sweets","Warehouse":"WH2","stock_level":102,"last_update":"2025-06-20T15:06:00Z"},
{"item_id":499,"name":"bell pepper","category":"Fashion","Warehouse":"WH1","stock_level":4,"last_update":"2025-06-02T11:16:22Z"},
{"item_id":500,"name":"couscous","category":"Groceries","Warehouse":"WH3","stock_level":33,"last_update":"2025-06-12T21:35:27Z"}]
